{
    "TopHitters":  [
                       {
                           "BatterID":  605141,
                           "BatterName":  "Mookie Betts",
                           "BatterTeamID":  111,
                           "BatterTeamName":  "Boston Red Sox",
                           "BatterHittingSide":  "Right",
                           "BatterRank":  1,
                           "BatterCurrentAverage":  ".432",
                           "BatterAvgHome":  ".279",
                           "BatterAvgAway":  ".251",
                           "BatterAvgDay":  ".259",
                           "BatterAvgNight":  ".266",
                           "BatterAvgGrass":  ".258",
                           "BatterAvgTurf":  ".312",
                           "BatterAvgToLefty":  ".450",
                           "BatterAvgToRighty":  ".382",
                           "BatterAvgMondays":  ".292",
                           "BatterAvgTuesdays":  ".284",
                           "BatterAvgWednesdays":  ".310",
                           "BatterAvgThursdays":  ".224",
                           "BatterAvgFridays":  ".260",
                           "BatterAvgSaturdays":  ".226",
                           "BatterAvgSundays":  ".253"
                       },
                       {
                           "BatterID":  429664,
                           "BatterName":  "Robinson Cano",
                           "BatterTeamID":  136,
                           "BatterTeamName":  "Seattle Mariners",
                           "BatterHittingSide":  "Left",
                           "BatterRank":  2,
                           "BatterCurrentAverage":  ".414",
                           "BatterAvgHome":  ".280",
                           "BatterAvgAway":  ".281",
                           "BatterAvgDay":  ".301",
                           "BatterAvgNight":  ".270",
                           "BatterAvgGrass":  ".280",
                           "BatterAvgTurf":  ".308",
                           "BatterAvgToLefty":  ".278",
                           "BatterAvgToRighty":  ".367",
                           "BatterAvgMondays":  ".141",
                           "BatterAvgTuesdays":  ".292",
                           "BatterAvgWednesdays":  ".371",
                           "BatterAvgThursdays":  ".323",
                           "BatterAvgFridays":  ".247",
                           "BatterAvgSaturdays":  ".256",
                           "BatterAvgSundays":  ".304"
                       },
                       {
                           "BatterID":  408045,
                           "BatterName":  "Joe Mauer",
                           "BatterTeamID":  142,
                           "BatterTeamName":  "Minnesota Twins",
                           "BatterHittingSide":  "Left",
                           "BatterRank":  3,
                           "BatterCurrentAverage":  ".407",
                           "BatterAvgHome":  ".300",
                           "BatterAvgAway":  ".309",
                           "BatterAvgDay":  ".316",
                           "BatterAvgNight":  ".299",
                           "BatterAvgGrass":  ".299",
                           "BatterAvgTurf":  ".435",
                           "BatterAvgToLefty":  ".370",
                           "BatterAvgToRighty":  ".328",
                           "BatterAvgMondays":  ".281",
                           "BatterAvgTuesdays":  ".256",
                           "BatterAvgWednesdays":  ".291",
                           "BatterAvgThursdays":  ".370",
                           "BatterAvgFridays":  ".274",
                           "BatterAvgSaturdays":  ".365",
                           "BatterAvgSundays":  ".296"
                       },
                       {
                           "BatterID":  544369,
                           "BatterName":  "Didi Gregorius",
                           "BatterTeamID":  147,
                           "BatterTeamName":  "New York Yankees",
                           "BatterHittingSide":  "Left",
                           "BatterRank":  4,
                           "BatterCurrentAverage":  ".389",
                           "BatterAvgHome":  ".251",
                           "BatterAvgAway":  ".321",
                           "BatterAvgDay":  ".278",
                           "BatterAvgNight":  ".292",
                           "BatterAvgGrass":  ".287",
                           "BatterAvgTurf":  ".283",
                           "BatterAvgToLefty":  ".256",
                           "BatterAvgToRighty":  ".281",
                           "BatterAvgMondays":  ".250",
                           "BatterAvgTuesdays":  ".329",
                           "BatterAvgWednesdays":  ".297",
                           "BatterAvgThursdays":  ".265",
                           "BatterAvgFridays":  ".271",
                           "BatterAvgSaturdays":  ".293",
                           "BatterAvgSundays":  ".288"
                       },
                       {
                           "BatterID":  656555,
                           "BatterName":  "Rhys Hoskins",
                           "BatterTeamID":  143,
                           "BatterTeamName":  "Philadelphia Phillies",
                           "BatterHittingSide":  "Right",
                           "BatterRank":  5,
                           "BatterCurrentAverage":  ".375",
                           "BatterAvgHome":  ".255",
                           "BatterAvgAway":  ".265",
                           "BatterAvgDay":  ".176",
                           "BatterAvgNight":  ".294",
                           "BatterAvgGrass":  ".259",
                           "BatterAvgTurf":  ".364",
                           "BatterAvgToLefty":  ".000",
                           "BatterAvgToRighty":  null,
                           "BatterAvgMondays":  ".294",
                           "BatterAvgTuesdays":  ".360",
                           "BatterAvgWednesdays":  ".261",
                           "BatterAvgThursdays":  ".304",
                           "BatterAvgFridays":  ".148",
                           "BatterAvgSaturdays":  ".321",
                           "BatterAvgSundays":  ".148"
                       },
                       {
                           "BatterID":  457763,
                           "BatterName":  "Buster Posey",
                           "BatterTeamID":  137,
                           "BatterTeamName":  "San Francisco Giants",
                           "BatterHittingSide":  "Right",
                           "BatterRank":  5,
                           "BatterCurrentAverage":  ".375",
                           "BatterAvgHome":  ".345",
                           "BatterAvgAway":  ".298",
                           "BatterAvgDay":  ".310",
                           "BatterAvgNight":  ".324",
                           "BatterAvgGrass":  ".320",
                           "BatterAvgTurf":  ".336",
                           "BatterAvgToLefty":  ".360",
                           "BatterAvgToRighty":  ".304",
                           "BatterAvgMondays":  ".379",
                           "BatterAvgTuesdays":  ".393",
                           "BatterAvgWednesdays":  ".281",
                           "BatterAvgThursdays":  ".351",
                           "BatterAvgFridays":  ".265",
                           "BatterAvgSaturdays":  ".253",
                           "BatterAvgSundays":  ".329"
                       },
                       {
                           "BatterID":  514888,
                           "BatterName":  "Jose Altuve",
                           "BatterTeamID":  117,
                           "BatterTeamName":  "Houston Astros",
                           "BatterHittingSide":  "Right",
                           "BatterRank":  7,
                           "BatterCurrentAverage":  ".370",
                           "BatterAvgHome":  ".311",
                           "BatterAvgAway":  ".381",
                           "BatterAvgDay":  ".358",
                           "BatterAvgNight":  ".341",
                           "BatterAvgGrass":  ".338",
                           "BatterAvgTurf":  ".462",
                           "BatterAvgToLefty":  ".313",
                           "BatterAvgToRighty":  ".421",
                           "BatterAvgMondays":  ".323",
                           "BatterAvgTuesdays":  ".319",
                           "BatterAvgWednesdays":  ".356",
                           "BatterAvgThursdays":  ".339",
                           "BatterAvgFridays":  ".333",
                           "BatterAvgSaturdays":  ".341",
                           "BatterAvgSundays":  ".398"
                       },
                       {
                           "BatterID":  593428,
                           "BatterName":  "Xander Bogaerts",
                           "BatterTeamID":  111,
                           "BatterTeamName":  "Boston Red Sox",
                           "BatterHittingSide":  "Right",
                           "BatterRank":  8,
                           "BatterCurrentAverage":  ".368",
                           "BatterAvgHome":  ".293",
                           "BatterAvgAway":  ".251",
                           "BatterAvgDay":  ".219",
                           "BatterAvgNight":  ".294",
                           "BatterAvgGrass":  ".275",
                           "BatterAvgTurf":  ".254",
                           "BatterAvgToLefty":  ".243",
                           "BatterAvgToRighty":  ".321",
                           "BatterAvgMondays":  ".182",
                           "BatterAvgTuesdays":  ".371",
                           "BatterAvgWednesdays":  ".280",
                           "BatterAvgThursdays":  ".242",
                           "BatterAvgFridays":  ".318",
                           "BatterAvgSaturdays":  ".244",
                           "BatterAvgSundays":  ".224"
                       },
                       {
                           "BatterID":  516416,
                           "BatterName":  "Jean Segura",
                           "BatterTeamID":  136,
                           "BatterTeamName":  "Seattle Mariners",
                           "BatterHittingSide":  "Right",
                           "BatterRank":  8,
                           "BatterCurrentAverage":  ".368",
                           "BatterAvgHome":  ".313",
                           "BatterAvgAway":  ".287",
                           "BatterAvgDay":  ".282",
                           "BatterAvgNight":  ".307",
                           "BatterAvgGrass":  ".300",
                           "BatterAvgTurf":  ".290",
                           "BatterAvgToLefty":  ".357",
                           "BatterAvgToRighty":  ".296",
                           "BatterAvgMondays":  ".213",
                           "BatterAvgTuesdays":  ".280",
                           "BatterAvgWednesdays":  ".349",
                           "BatterAvgThursdays":  ".382",
                           "BatterAvgFridays":  ".311",
                           "BatterAvgSaturdays":  ".294",
                           "BatterAvgSundays":  ".253"
                       },
                       {
                           "BatterID":  621020,
                           "BatterName":  "Dansby Swanson",
                           "BatterTeamID":  144,
                           "BatterTeamName":  "Atlanta Braves",
                           "BatterHittingSide":  "Right",
                           "BatterRank":  10,
                           "BatterCurrentAverage":  ".366",
                           "BatterAvgHome":  ".237",
                           "BatterAvgAway":  ".227",
                           "BatterAvgDay":  ".258",
                           "BatterAvgNight":  ".218",
                           "BatterAvgGrass":  ".227",
                           "BatterAvgTurf":  ".500",
                           "BatterAvgToLefty":  ".223",
                           "BatterAvgToRighty":  ".228",
                           "BatterAvgMondays":  ".250",
                           "BatterAvgTuesdays":  ".273",
                           "BatterAvgWednesdays":  ".207",
                           "BatterAvgThursdays":  ".176",
                           "BatterAvgFridays":  ".187",
                           "BatterAvgSaturdays":  ".309",
                           "BatterAvgSundays":  ".218"
                       },
                       {
                           "BatterID":  592743,
                           "BatterName":  "Andrelton Simmons",
                           "BatterTeamID":  108,
                           "BatterTeamName":  "Los Angeles Angels",
                           "BatterHittingSide":  "Right",
                           "BatterRank":  11,
                           "BatterCurrentAverage":  ".365",
                           "BatterAvgHome":  ".265",
                           "BatterAvgAway":  ".291",
                           "BatterAvgDay":  ".283",
                           "BatterAvgNight":  ".277",
                           "BatterAvgGrass":  ".271",
                           "BatterAvgTurf":  ".429",
                           "BatterAvgToLefty":  ".231",
                           "BatterAvgToRighty":  ".270",
                           "BatterAvgMondays":  ".365",
                           "BatterAvgTuesdays":  ".253",
                           "BatterAvgWednesdays":  ".282",
                           "BatterAvgThursdays":  ".246",
                           "BatterAvgFridays":  ".296",
                           "BatterAvgSaturdays":  ".245",
                           "BatterAvgSundays":  ".292"
                       },
                       {
                           "BatterID":  434670,
                           "BatterName":  "Hanley Ramirez",
                           "BatterTeamID":  111,
                           "BatterTeamName":  "Boston Red Sox",
                           "BatterHittingSide":  "Right",
                           "BatterRank":  12,
                           "BatterCurrentAverage":  ".359",
                           "BatterAvgHome":  ".238",
                           "BatterAvgAway":  ".246",
                           "BatterAvgDay":  ".269",
                           "BatterAvgNight":  ".232",
                           "BatterAvgGrass":  ".230",
                           "BatterAvgTurf":  ".328",
                           "BatterAvgToLefty":  ".083",
                           "BatterAvgToRighty":  ".204",
                           "BatterAvgMondays":  ".214",
                           "BatterAvgTuesdays":  ".229",
                           "BatterAvgWednesdays":  ".182",
                           "BatterAvgThursdays":  ".214",
                           "BatterAvgFridays":  ".269",
                           "BatterAvgSaturdays":  ".241",
                           "BatterAvgSundays":  ".324"
                       },
                       {
                           "BatterID":  572008,
                           "BatterName":  "Chris Owings",
                           "BatterTeamID":  109,
                           "BatterTeamName":  "Arizona Diamondbacks",
                           "BatterHittingSide":  "Right",
                           "BatterRank":  13,
                           "BatterCurrentAverage":  ".353",
                           "BatterAvgHome":  ".315",
                           "BatterAvgAway":  ".219",
                           "BatterAvgDay":  ".264",
                           "BatterAvgNight":  ".270",
                           "BatterAvgGrass":  ".268",
                           "BatterAvgTurf":  ".219",
                           "BatterAvgToLefty":  ".258",
                           "BatterAvgToRighty":  null,
                           "BatterAvgMondays":  ".267",
                           "BatterAvgTuesdays":  ".293",
                           "BatterAvgWednesdays":  ".278",
                           "BatterAvgThursdays":  ".192",
                           "BatterAvgFridays":  ".317",
                           "BatterAvgSaturdays":  ".245",
                           "BatterAvgSundays":  ".273"
                       },
                       {
                           "BatterID":  520471,
                           "BatterName":  "Freddy Galvis",
                           "BatterTeamID":  135,
                           "BatterTeamName":  "San Diego Padres",
                           "BatterHittingSide":  "Switch",
                           "BatterRank":  14,
                           "BatterCurrentAverage":  ".350",
                           "BatterAvgHome":  ".260",
                           "BatterAvgAway":  ".250",
                           "BatterAvgDay":  ".269",
                           "BatterAvgNight":  ".247",
                           "BatterAvgGrass":  ".255",
                           "BatterAvgTurf":  ".246",
                           "BatterAvgToLefty":  ".255",
                           "BatterAvgToRighty":  ".255",
                           "BatterAvgMondays":  ".197",
                           "BatterAvgTuesdays":  ".204",
                           "BatterAvgWednesdays":  ".287",
                           "BatterAvgThursdays":  ".286",
                           "BatterAvgFridays":  ".242",
                           "BatterAvgSaturdays":  ".269",
                           "BatterAvgSundays":  ".287"
                       },
                       {
                           "BatterID":  656305,
                           "BatterName":  "Matt Chapman",
                           "BatterTeamID":  133,
                           "BatterTeamName":  "Oakland Athletics",
                           "BatterHittingSide":  "Right",
                           "BatterRank":  15,
                           "BatterCurrentAverage":  ".349",
                           "BatterAvgHome":  ".284",
                           "BatterAvgAway":  ".183",
                           "BatterAvgDay":  ".257",
                           "BatterAvgNight":  ".220",
                           "BatterAvgGrass":  ".242",
                           "BatterAvgTurf":  ".077",
                           "BatterAvgToLefty":  ".308",
                           "BatterAvgToRighty":  ".258",
                           "BatterAvgMondays":  ".083",
                           "BatterAvgTuesdays":  ".214",
                           "BatterAvgWednesdays":  ".167",
                           "BatterAvgThursdays":  ".143",
                           "BatterAvgFridays":  ".277",
                           "BatterAvgSaturdays":  ".347",
                           "BatterAvgSundays":  ".302"
                       },
                       {
                           "BatterID":  462101,
                           "BatterName":  "Elvis Andrus",
                           "BatterTeamID":  140,
                           "BatterTeamName":  "Texas Rangers",
                           "BatterHittingSide":  "Right",
                           "BatterRank":  16,
                           "BatterCurrentAverage":  ".347",
                           "BatterAvgHome":  ".299",
                           "BatterAvgAway":  ".295",
                           "BatterAvgDay":  ".289",
                           "BatterAvgNight":  ".300",
                           "BatterAvgGrass":  ".287",
                           "BatterAvgTurf":  ".439",
                           "BatterAvgToLefty":  ".214",
                           "BatterAvgToRighty":  ".247",
                           "BatterAvgMondays":  ".286",
                           "BatterAvgTuesdays":  ".280",
                           "BatterAvgWednesdays":  ".352",
                           "BatterAvgThursdays":  ".203",
                           "BatterAvgFridays":  ".350",
                           "BatterAvgSaturdays":  ".280",
                           "BatterAvgSundays":  ".287"
                       },
                       {
                           "BatterID":  546318,
                           "BatterName":  "Odubel Herrera",
                           "BatterTeamID":  143,
                           "BatterTeamName":  "Philadelphia Phillies",
                           "BatterHittingSide":  "Left",
                           "BatterRank":  17,
                           "BatterCurrentAverage":  ".344",
                           "BatterAvgHome":  ".297",
                           "BatterAvgAway":  ".265",
                           "BatterAvgDay":  ".280",
                           "BatterAvgNight":  ".282",
                           "BatterAvgGrass":  ".281",
                           "BatterAvgTurf":  ".345",
                           "BatterAvgToLefty":  ".288",
                           "BatterAvgToRighty":  ".279",
                           "BatterAvgMondays":  ".328",
                           "BatterAvgTuesdays":  ".325",
                           "BatterAvgWednesdays":  ".244",
                           "BatterAvgThursdays":  ".213",
                           "BatterAvgFridays":  ".266",
                           "BatterAvgSaturdays":  ".242",
                           "BatterAvgSundays":  ".359"
                       },
                       {
                           "BatterID":  592567,
                           "BatterName":  "Colin Moran",
                           "BatterTeamID":  134,
                           "BatterTeamName":  "Pittsburgh Pirates",
                           "BatterHittingSide":  "Left",
                           "BatterRank":  17,
                           "BatterCurrentAverage":  ".344",
                           "BatterAvgHome":  ".375",
                           "BatterAvgAway":  ".364",
                           "BatterAvgDay":  ".333",
                           "BatterAvgNight":  ".000",
                           "BatterAvgGrass":  ".364",
                           "BatterAvgTurf":  ".500",
                           "BatterAvgToLefty":  null,
                           "BatterAvgToRighty":  null,
                           "BatterAvgMondays":  ".000",
                           "BatterAvgTuesdays":  ".000",
                           "BatterAvgWednesdays":  ".000",
                           "BatterAvgThursdays":  "",
                           "BatterAvgFridays":  ".500",
                           "BatterAvgSaturdays":  ".500",
                           "BatterAvgSundays":  ".500"
                       },
                       {
                           "BatterID":  475247,
                           "BatterName":  "Ryan Flaherty",
                           "BatterTeamID":  144,
                           "BatterTeamName":  "Atlanta Braves",
                           "BatterHittingSide":  "Left",
                           "BatterRank":  19,
                           "BatterCurrentAverage":  ".343",
                           "BatterAvgHome":  ".167",
                           "BatterAvgAway":  ".250",
                           "BatterAvgDay":  ".300",
                           "BatterAvgNight":  ".111",
                           "BatterAvgGrass":  ".229",
                           "BatterAvgTurf":  ".000",
                           "BatterAvgToLefty":  ".000",
                           "BatterAvgToRighty":  ".000",
                           "BatterAvgMondays":  ".000",
                           "BatterAvgTuesdays":  ".000",
                           "BatterAvgWednesdays":  ".200",
                           "BatterAvgThursdays":  ".200",
                           "BatterAvgFridays":  "",
                           "BatterAvgSaturdays":  ".250",
                           "BatterAvgSundays":  ".375"
                       },
                       {
                           "BatterID":  435062,
                           "BatterName":  "Howie Kendrick",
                           "BatterTeamID":  120,
                           "BatterTeamName":  "Washington Nationals",
                           "BatterHittingSide":  "Right",
                           "BatterRank":  19,
                           "BatterCurrentAverage":  ".343",
                           "BatterAvgHome":  ".450",
                           "BatterAvgAway":  ".355",
                           "BatterAvgDay":  ".268",
                           "BatterAvgNight":  ".211",
                           "BatterAvgGrass":  ".280",
                           "BatterAvgTurf":  ".000",
                           "BatterAvgToLefty":  ".296",
                           "BatterAvgToRighty":  ".329",
                           "BatterAvgMondays":  ".222",
                           "BatterAvgTuesdays":  ".154",
                           "BatterAvgWednesdays":  ".269",
                           "BatterAvgThursdays":  ".400",
                           "BatterAvgFridays":  ".352",
                           "BatterAvgSaturdays":  ".409",
                           "BatterAvgSundays":  ".400"
                       },
                       {
                           "BatterID":  572816,
                           "BatterName":  "Corey Dickerson",
                           "BatterTeamID":  134,
                           "BatterTeamName":  "Pittsburgh Pirates",
                           "BatterHittingSide":  "Left",
                           "BatterRank":  21,
                           "BatterCurrentAverage":  ".342",
                           "BatterAvgHome":  ".265",
                           "BatterAvgAway":  ".297",
                           "BatterAvgDay":  ".263",
                           "BatterAvgNight":  ".292",
                           "BatterAvgGrass":  ".288",
                           "BatterAvgTurf":  ".277",
                           "BatterAvgToLefty":  ".286",
                           "BatterAvgToRighty":  ".257",
                           "BatterAvgMondays":  ".302",
                           "BatterAvgTuesdays":  ".256",
                           "BatterAvgWednesdays":  ".307",
                           "BatterAvgThursdays":  ".279",
                           "BatterAvgFridays":  ".275",
                           "BatterAvgSaturdays":  ".265",
                           "BatterAvgSundays":  ".294"
                       },
                       {
                           "BatterID":  543829,
                           "BatterName":  "Dee Gordon",
                           "BatterTeamID":  136,
                           "BatterTeamName":  "Seattle Mariners",
                           "BatterHittingSide":  "Left",
                           "BatterRank":  21,
                           "BatterCurrentAverage":  ".342",
                           "BatterAvgHome":  ".332",
                           "BatterAvgAway":  ".287",
                           "BatterAvgDay":  ".311",
                           "BatterAvgNight":  ".307",
                           "BatterAvgGrass":  ".307",
                           "BatterAvgTurf":  ".500",
                           "BatterAvgToLefty":  ".316",
                           "BatterAvgToRighty":  ".305",
                           "BatterAvgMondays":  ".304",
                           "BatterAvgTuesdays":  ".317",
                           "BatterAvgWednesdays":  ".286",
                           "BatterAvgThursdays":  ".361",
                           "BatterAvgFridays":  ".296",
                           "BatterAvgSaturdays":  ".264",
                           "BatterAvgSundays":  ".354"
                       },
                       {
                           "BatterID":  542340,
                           "BatterName":  "Jonathan Villar",
                           "BatterTeamID":  158,
                           "BatterTeamName":  "Milwaukee Brewers",
                           "BatterHittingSide":  "Switch",
                           "BatterRank":  21,
                           "BatterCurrentAverage":  ".342",
                           "BatterAvgHome":  ".262",
                           "BatterAvgAway":  ".213",
                           "BatterAvgDay":  ".250",
                           "BatterAvgNight":  ".235",
                           "BatterAvgGrass":  ".242",
                           "BatterAvgTurf":  ".200",
                           "BatterAvgToLefty":  ".264",
                           "BatterAvgToRighty":  ".236",
                           "BatterAvgMondays":  ".114",
                           "BatterAvgTuesdays":  ".138",
                           "BatterAvgWednesdays":  ".327",
                           "BatterAvgThursdays":  ".262",
                           "BatterAvgFridays":  ".236",
                           "BatterAvgSaturdays":  ".275",
                           "BatterAvgSundays":  ".308"
                       },
                       {
                           "BatterID":  452678,
                           "BatterName":  "Asdrubal Cabrera",
                           "BatterTeamID":  121,
                           "BatterTeamName":  "New York Mets",
                           "BatterHittingSide":  "Switch",
                           "BatterRank":  24,
                           "BatterCurrentAverage":  ".341",
                           "BatterAvgHome":  ".245",
                           "BatterAvgAway":  ".308",
                           "BatterAvgDay":  ".224",
                           "BatterAvgNight":  ".298",
                           "BatterAvgGrass":  ".280",
                           "BatterAvgTurf":  ".275",
                           "BatterAvgToLefty":  ".392",
                           "BatterAvgToRighty":  ".240",
                           "BatterAvgMondays":  ".306",
                           "BatterAvgTuesdays":  ".320",
                           "BatterAvgWednesdays":  ".282",
                           "BatterAvgThursdays":  ".280",
                           "BatterAvgFridays":  ".337",
                           "BatterAvgSaturdays":  ".242",
                           "BatterAvgSundays":  ".179"
                       },
                       {
                           "BatterID":  605137,
                           "BatterName":  "Josh Bell",
                           "BatterTeamID":  134,
                           "BatterTeamName":  "Pittsburgh Pirates",
                           "BatterHittingSide":  "Switch",
                           "BatterRank":  25,
                           "BatterCurrentAverage":  ".333",
                           "BatterAvgHome":  ".246",
                           "BatterAvgAway":  ".263",
                           "BatterAvgDay":  ".256",
                           "BatterAvgNight":  ".254",
                           "BatterAvgGrass":  ".254",
                           "BatterAvgTurf":  ".400",
                           "BatterAvgToLefty":  ".256",
                           "BatterAvgToRighty":  ".251",
                           "BatterAvgMondays":  ".242",
                           "BatterAvgTuesdays":  ".171",
                           "BatterAvgWednesdays":  ".230",
                           "BatterAvgThursdays":  ".276",
                           "BatterAvgFridays":  ".354",
                           "BatterAvgSaturdays":  ".264",
                           "BatterAvgSundays":  ".227"
                       }
                   ]
}
